examplepkgjanesmith/__init__.py
examplepkgjanesmith-0.1.dist-info/METADATA
examplepkgjanesmith-0.1.dist-info/WHEEL
examplepkgjanesmith-0.1.dist-info/top_level.txt
examplepkgjanesmith-0.1.dist-info/RECORD
